panelsplit/__init__.py
panelsplit/application.py
panelsplit/cross_validation.py
panelsplit/pipeline.py
panelsplit/plot.py
panelsplit/utils/__init__.py
panelsplit/utils/utils.py
panelsplit/utils/validation.py
panelsplit-1.1.1.dist-info/METADATA
panelsplit-1.1.1.dist-info/WHEEL
panelsplit-1.1.1.dist-info/licenses/LICENSE
panelsplit-1.1.1.dist-info/RECORD
