Metadata-Version: 2.4
Name: panelsplit
Version: 1.1.1
Summary: A tool for panel data analysis.
Project-URL: Homepage, https://github.com/4Freye/panelsplit
Project-URL: Repository, https://github.com/4Freye/panelsplit
Project-URL: Documentation, https://4freye.github.io/panelsplit/panelsplit.html
Author-email: panelsplit developers <eric.frey@bse.eu>
License: MIT
License-File: LICENSE
Classifier: License :: OSI Approved :: MIT License
Classifier: Operating System :: OS Independent
Classifier: Programming Language :: Python :: 3
Requires-Python: >=3.8
Requires-Dist: joblib>=1.0.1
Requires-Dist: matplotlib>=3.4.3
Requires-Dist: narwhals>=1.42.1
Requires-Dist: numpy>=1.21.0
Requires-Dist: pandas>=1.3.0
Requires-Dist: scikit-learn>=0.24.2
Requires-Dist: tqdm>=4.67.1
